imppkg/__init__.py
imppkg/data.json
imppkg/harmonic_mean.c
imppkg/harmonic_mean.cpython-311-darwin.so
imppkg/harmonic_mean.pyx
imppkg/harmony.py
imppkg/hello.py
imppkg/__pycache__/__init__.cpython-310.pyc
imppkg/__pycache__/harmony.cpython-310.pyc
pubpypack_harmony_alejandro_palacios-0.0.1.dist-info/LICENSE
pubpypack_harmony_alejandro_palacios-0.0.1.dist-info/METADATA
pubpypack_harmony_alejandro_palacios-0.0.1.dist-info/WHEEL
pubpypack_harmony_alejandro_palacios-0.0.1.dist-info/entry_points.txt
pubpypack_harmony_alejandro_palacios-0.0.1.dist-info/top_level.txt
pubpypack_harmony_alejandro_palacios-0.0.1.dist-info/RECORD
