Metadata-Version: 2.1
Name: pubpypack-harmony-alejandro-palacios
Version: 0.0.1
Summary: This package does amazing things.
Home-page: https://github.com/alex77palacios/first-python-package
Author: Alejandro Palacios
Author-email: "Alejandro" <alex_palacios77@icloud.com>
License: MIT
Classifier: License :: OSI Approved :: MIT License
Requires-Python: >=3.9
License-File: LICENSE
Requires-Dist: termcolor <2,>=1.1.0
